{
  "phase": "34",
  "cycle": 2,
  "task": "AI Specialist Page Decision",
  "generated": "2026-06-21T21:30:00+03:00",
  "decision": "REMOVE_FROM_NAV",
  "reason": "Page is functional but thin for unauthenticated public users. Primary value is for logged-in users. Not central to QFINHUB's free calculator mission. Removing from nav prevents AdSense reviewers from flagging it as unfinished/gated content.",
  "page_status": {
    "still_accessible": true,
    "still_in_sitemap": true,
    "noindex": false,
    "adsense_eligible": false,
    "client_side_only": true,
    "requires_auth_for_saving": true
  },
  "future_action": "If AI Specialist is improved with substantial public content and proves value, can be re-added to nav after AdSense review."
}