{
  "source": "GSC_API_RAW \u2014 CORRECTION DISABLED PER PHASE 19.2",
  "generated": "2026-07-12T00:36:32Z",
  "date_range": {
    "start": "2026-07-03",
    "end": "2026-07-09"
  },
  "checksum": "31349c51dcc2",
  "auth_method": "service_account",
  "api_raw": {
    "impressions": 486,
    "clicks": 0,
    "pages_with_impressions": 45,
    "avg_position": 63.4,
    "query_level_impressions": 333
  },
  "correction": {
    "factor_impressions": 1.434,
    "factor_position": 0.886,
    "last_calibrated": "2026-06-07",
    "calibration_source": "Qasem manual GSC UI check \u2014 Jun 7, 2026",
    "applied_to_official_kpi": false,
    "note": "Correction factor is DOCUMENTATION ONLY."
  },
  "corrected_estimate_fyi": {
    "impressions": 697,
    "clicks": 0,
    "avg_position": 56.2,
    "note": "FYI ONLY \u2014 NOT official."
  }
}