{
  "title": "Risky Cron Status \u2014 Phase 14A.2 Final",
  "generated": "2026-06-04T19:31:52.239495Z",
  "all_paused": true,
  "paused_list": [
    {
      "name": "Blog Agent",
      "id": "e3d7d3fcb7c9",
      "status": "PAUSED \u2705"
    },
    {
      "name": "Scenario Generator",
      "id": "7edc3f28a918",
      "status": "PAUSED \u2705"
    },
    {
      "name": "Scenario Upgrades",
      "id": "291b8aa4f5d0",
      "status": "PAUSED \u2705"
    },
    {
      "name": "SEO Indexing Engine",
      "id": "14d3d631f9ba",
      "status": "PAUSED \u2705"
    },
    {
      "name": "Sitemap Ping",
      "id": "7ba22a836377",
      "status": "PAUSED \u2705"
    },
    {
      "name": "Widget Outreach",
      "id": "43438e317a61",
      "status": "PAUSED \u2705 (14A.1)"
    },
    {
      "name": "Newsjacking Bot",
      "id": "d006e3318401",
      "status": "PAUSED \u2705 (14A.1)"
    },
    {
      "name": "Pinterest Pin Gen (3:30PM)",
      "id": "defdde75ea1f",
      "status": "PAUSED \u2705"
    },
    {
      "name": "Pinterest Pin Gen (3AM)",
      "id": "5c46309c02c0",
      "status": "PAUSED \u2705"
    },
    {
      "name": "Pinterest Morning Post",
      "id": "f803aceaa0a7",
      "status": "PAUSED \u2705"
    },
    {
      "name": "Pinterest Evening Post",
      "id": "7c97577dbd84",
      "status": "PAUSED \u2705"
    },
    {
      "name": "X Morning",
      "id": "8a229e1e731b",
      "status": "PAUSED \u2705"
    },
    {
      "name": "X Noon",
      "id": "be62779e2dc0",
      "status": "PAUSED \u2705"
    },
    {
      "name": "X Afternoon",
      "id": "2bd0d2e26dc8",
      "status": "PAUSED \u2705"
    },
    {
      "name": "X Evening",
      "id": "2e55e62a79a8",
      "status": "PAUSED \u2705"
    },
    {
      "name": "X Night",
      "id": "6320859ceb69",
      "status": "PAUSED \u2705"
    },
    {
      "name": "X Self-Tweet",
      "id": "fb1ea44cc2dc",
      "status": "PAUSED \u2705"
    }
  ],
  "total_paused": 17,
  "confirmation": "All risky automations remain PAUSED. No re-enablements."
}